NeuralNet/DerivableFunction.py
NeuralNet/__init__.py
NeuralNet/Layers/ActivationLayer.py
NeuralNet/Layers/BaseLayer.py
NeuralNet/Layers/Construct.py
NeuralNet/Layers/LossLayer.py
NeuralNet/Layers/WeightLayer.py
NeuralNet/Layers/WeightLayerTypes.py
NeuralNet/Layers/__init__.py
NeuralNet/Layers/Activation/Activation.py
NeuralNet/Layers/Activation/ActivationTypes.py
NeuralNet/Layers/Activation/__init__.py
NeuralNet/Layers/Initializers/InitializerTypes.py
NeuralNet/Layers/Initializers/Initializers.py
NeuralNet/Layers/Initializers/__init__.py
NeuralNet/Layers/Loss/Loss.py
NeuralNet/Layers/Loss/LossTypes.py
NeuralNet/Layers/Loss/__init__.py
NeuralNet/MNIST/MNIST_Loader.py
NeuralNet/MNIST/__init__.py
NeuralNet/Networks/FeedForwardNeuralNetwork.py
NeuralNet/Networks/__init__.py
NeuralNetToolkit-1.0.2.data/data/NeuralNet/MNIST/archive/t10k-images.idx3-ubyte
NeuralNetToolkit-1.0.2.data/data/NeuralNet/MNIST/archive/t10k-labels.idx1-ubyte
NeuralNetToolkit-1.0.2.data/data/NeuralNet/MNIST/archive/train-images.idx3-ubyte
NeuralNetToolkit-1.0.2.data/data/NeuralNet/MNIST/archive/train-labels.idx1-ubyte
NeuralNetToolkit-1.0.2.data/data/NeuralNet/MNIST/archive/t10k-images-idx3-ubyte/t10k-images-idx3-ubyte
NeuralNetToolkit-1.0.2.data/data/NeuralNet/MNIST/archive/t10k-labels-idx1-ubyte/t10k-labels-idx1-ubyte
NeuralNetToolkit-1.0.2.data/data/NeuralNet/MNIST/archive/train-images-idx3-ubyte/train-images-idx3-ubyte
NeuralNetToolkit-1.0.2.data/data/NeuralNet/MNIST/archive/train-labels-idx1-ubyte/train-labels-idx1-ubyte
NeuralNetToolkit-1.0.2.dist-info/METADATA
NeuralNetToolkit-1.0.2.dist-info/WHEEL
NeuralNetToolkit-1.0.2.dist-info/top_level.txt
NeuralNetToolkit-1.0.2.dist-info/RECORD
